sc_kernel/__init__.py
sc_kernel/__main__.py
sc_kernel/kernel.json
sc_kernel/kernel.py
sc_kernel/images/logo-32x32.png
sc_kernel/images/logo-64x64.png
sc_kernel-0.5.0.data/data/share/jupyter/kernels/sc_kernel/kernel.json
sc_kernel-0.5.0.data/data/share/jupyter/kernels/sc_kernel/logo-32x32.png
sc_kernel-0.5.0.data/data/share/jupyter/kernels/sc_kernel/logo-64x64.png
sc_kernel-0.5.0.dist-info/licenses/LICENSE
sc_kernel-0.5.0.dist-info/METADATA
sc_kernel-0.5.0.dist-info/WHEEL
sc_kernel-0.5.0.dist-info/top_level.txt
sc_kernel-0.5.0.dist-info/RECORD
