Metadata-Version: 2.4
Name: sc_kernel
Version: 0.5.0
Summary: SuperCollider kernel for Jupyter
Author: Dennis Scheiba
License: BSD
Classifier: Programming Language :: Python :: 3
Classifier: Operating System :: OS Independent
Classifier: Framework :: IPython
Classifier: License :: OSI Approved :: BSD License
Classifier: Topic :: System :: Shells
Classifier: Topic :: Multimedia :: Sound/Audio :: Sound Synthesis
Requires-Python: >=3.10
License-File: LICENSE
Requires-Dist: metakernel<0.31,>=0.23.0
Requires-Dist: ipython<10.0,>=4.0
Requires-Dist: pygments<3.0
Requires-Dist: jupyterlab<5.0,>=3.0
Requires-Dist: jupyter_server<3.0,>2.0
Provides-Extra: dev
Requires-Dist: coverage==5.2.1; extra == "dev"
Requires-Dist: flake8<=6.0.0; extra == "dev"
Requires-Dist: unittest-xml-reporting==3.0.4; extra == "dev"
Requires-Dist: mypy<=1.0.0; extra == "dev"
Requires-Dist: pre-commit==2.17.0; extra == "dev"
Requires-Dist: black<=23.1.0; extra == "dev"
Dynamic: license-file
